govctl/__init__.py
govctl/config.py
govctl/main.py
govctl/queue.py
govctl-0.1.2.dist-info/entry_points.txt
govctl-0.1.2.dist-info/WHEEL
govctl-0.1.2.dist-info/METADATA
govctl-0.1.2.dist-info/RECORD
